shippai/__init__.py
shippai-0.3.2.dist-info/METADATA
shippai-0.3.2.dist-info/RECORD
shippai-0.3.2.dist-info/WHEEL
shippai-0.3.2.dist-info/top_level.txt
