Metadata-Version: 2.1
Name: shippai
Version: 0.3.2
Summary: Interface with Rust errors seamlessly
Home-page: https://github.com/untitaker/shippai
Author: Markus Unterwaditzer
Author-email: markus-python@unterwaditzer.net
License: MIT
Platform: UNKNOWN
Classifier: License :: OSI Approved :: MIT License
